lomi/__init__.py
lomi/client.py
lomi/exceptions.py
lomi/py.typed
lomi_sdk-1.3.0.dist-info/METADATA
lomi_sdk-1.3.0.dist-info/WHEEL
lomi_sdk-1.3.0.dist-info/top_level.txt
lomi_sdk-1.3.0.dist-info/RECORD
