Metadata-Version: 2.1
Name: lomi-sdk
Version: 1.3.0
Summary: lomi. API
Home-page: UNKNOWN
Author: lomi. Support
Author-email: hello@lomi.africa
License: MIT
Keywords: OpenAPI,OpenAPI-Generator,lomi. API
Platform: UNKNOWN
Requires-Dist: urllib3<3.0.0,>=2.1.0
Requires-Dist: python-dateutil>=2.8.2
Requires-Dist: pydantic>=2
Requires-Dist: typing-extensions>=4.7.1
